Workbook

Sheet Planilha1
B7: Configurações
B8: Salário | D8: 1800
B9: Rendimento Carteira | D9: 0.005
B10: Sugestão de Investimento | D10: =D8*30% -> 540
B12: INVESTIMENTO MENSAL
B13: Quanto investir por mês? | D13: 200
B14: Por Quantos Anos? | D14: 5
B15: Taxa de Rendimento mensal?
B16: Patrimônio acumulado? | D16: =FV(D15,D14*12,D13*-1) -> #VALUE!
B17: Dividendos Mensais | D17: =D16*1% -> #VALUE!
B19: Cenánarios | C19: Valor acumulado | D19: Dividendos
A20: 2 | B20: Quanto em 2 Anos? | C20: =FV($D$9,$A20*12,$D$13*-1) -> 5086.391 | D20: =C20*1% -> 50.86391
A21: 5 | B21: Quanto em 5 Anos? | C21: =FV($D$9,$A21*12,$D$13*-1) -> 13954.006 | D21: =C21*1% -> 139.54006
A22: 10 | B22: Quanto em 10 Anos? | C22: =FV($D$9,$A22*12,$D$13*-1) -> 32775.869 | D22: =C22*1% -> 327.75869
A23: 20 | B23: Quanto em 20 Anos? | C23: =FV($D$9,$A23*12,$D$13*-1) -> 92408.179 | D23: =C23*1% -> 924.08179
A24: 30 | B24: Quanto em 30Anos? | C24: =FV($D$9,$A24*12,$D$13*-1) -> 200903.01 | D24: =C24*1% -> 2009.0301
B27: PERFIL | C27: Agressivo
B28: VALOR A SER INVESTIDO POR MÊS | C28: =D13 -> 200
B30: TIPOS DE FII | C30: Percentual Sugerido | D30: Valores
B31: PAPEL | C31: =VLOOKUP(C$27&"-"&B31,Planilha2!$B:$E,4,FALSE) -> 0.5 | D31: =C31*$C$28 -> 100
B32: TIJOLO | C32: =VLOOKUP(C$27&"-"&B32,Planilha2!$B:$E,4,FALSE) -> 0.1 | D32: =C32*$C$28 -> 20
B33: HÍBRIDOS | C33: =VLOOKUP(C$27&"-"&B33,Planilha2!$B:$E,4,FALSE) -> 0.05 | D33: =C33*$C$28 -> 10
B34: FOFs | C34: =VLOOKUP(C$27&"-"&B34,Planilha2!$B:$E,4,FALSE) -> 0.05 | D34: =C34*$C$28 -> 10
B35: DESENVOLVIMENTO | C35: =VLOOKUP(C$27&"-"&B35,Planilha2!$B:$E,4,FALSE) -> 0.2 | D35: =C35*$C$28 -> 40
B36: HORTELARIAS | C36: =VLOOKUP(C$27&"-"&B36,Planilha2!$B:$E,4,FALSE) -> 0.1 | D36: =C36*$C$28 -> 20
D37: =SUM(D31:D36) -> 200
B39: SUGESTÃO DE FUNDOS: | D39: fonte Investidor10.com
B40: PAPEL | D40: MXRF11,VGHF11,KNCR11
B41: TIJOLO | D41: GARE11,XPML11,HGLG11
B42: HÍBRIDOS | D42: MXRF11,GARE11,VGHF11
B43: FOFs | D43: KISU11,HFOF11,RBRX11
B44: DESENVOLVIMENTO | D44: TGAR11,MFII11,HDOF11
B45: HORTELARIAS | D45: HTMX11,MGHT11

Sheet Planilha2
B3: CHAVE | C3: PERFIL | D3: TIPOS DE FII | E3: % | H3: =$B4 -> Conservador-PAPEL | I3: =VLOOKUP(H3,$B:$E,4,FALSE) -> 0.3
B4: =C4&"-"&D4 -> Conservador-PAPEL | C4: Conservador | D4: PAPEL | E4: 0.3 | H4: =$B5 -> Conservador-TIJOLO | I4: =VLOOKUP(H4,$B:$E,4,FALSE) -> 0.5
B5: =C5&"-"&D5 -> Conservador-TIJOLO | C5: Conservador | D5: TIJOLO | E5: 0.5 | H5: =$B6 -> Conservador-HÍBRIDOS | I5: =VLOOKUP(H5,$B:$E,4,FALSE) -> 0.1
B6: =C6&"-"&D6 -> Conservador-HÍBRIDOS | C6: Conservador | D6: HÍBRIDOS | E6: 0.1 | H6: =$B7 -> Conservador-FOFs | I6: =VLOOKUP(H6,$B:$E,4,FALSE) -> 0.1
B7: =C7&"-"&D7 -> Conservador-FOFs | C7: Conservador | D7: FOFs | E7: 0.1 | H7: =$B8 -> Conservador-DESENVOLVIMENTO | I7: =VLOOKUP(H7,$B:$E,4,FALSE) -> 0
B8: =C8&"-"&D8 -> Conservador-DESENVOLVIMENTO | C8: Conservador | D8: DESENVOLVIMENTO | E8: 0 | H8: =$B9 -> Conservador-HORTELARIAS | I8: =VLOOKUP(H8,$B:$E,4,FALSE) -> 0
B9: =C9&"-"&D9 -> Conservador-HORTELARIAS | C9: Conservador | D9: HORTELARIAS | E9: 0 | H9: =$B10 -> Moderado-PAPEL | I9: =VLOOKUP(H9,$B:$E,4,FALSE) -> 0.32
B10: =C10&"-"&D10 -> Moderado-PAPEL | C10: Moderado | D10: PAPEL | E10: 0.32 | H10: =$B11 -> Moderado-TIJOLO | I10: =VLOOKUP(H10,$B:$E,4,FALSE) -> 0.35
B11: =C11&"-"&D11 -> Moderado-TIJOLO | C11: Moderado | D11: TIJOLO | E11: 0.35 | H11: =$B12 -> Moderado-HÍBRIDOS | I11: =VLOOKUP(H11,$B:$E,4,FALSE) -> 0.08
B12: =C12&"-"&D12 -> Moderado-HÍBRIDOS | C12: Moderado | D12: HÍBRIDOS | E12: 0.08 | H12: =$B13 -> Moderado-FOFs | I12: =VLOOKUP(H12,$B:$E,4,FALSE) -> 0.05
B13: =C13&"-"&D13 -> Moderado-FOFs | C13: Moderado | D13: FOFs | E13: 0.05 | H13: =$B14 -> Moderado-DESENVOLVIMENTO | I13: =VLOOKUP(H13,$B:$E,4,FALSE) -> 0.1
B14: =C14&"-"&D14 -> Moderado-DESENVOLVIMENTO | C14: Moderado | D14: DESENVOLVIMENTO | E14: 0.1 | H14: =$B15 -> Moderado-HORTELARIAS | I14: =VLOOKUP(H14,$B:$E,4,FALSE) -> 0.1
B15: =C15&"-"&D15 -> Moderado-HORTELARIAS | C15: Moderado | D15: HORTELARIAS | E15: 0.1 | H15: =$B16 -> Agressivo-PAPEL | I15: =VLOOKUP(H15,$B:$E,4,FALSE) -> 0.5
... B20: =C20&"-"&D20 -> Agressivo-DESENVOLVIMENTO | C20: Agressivo | D20: DESENVOLVIMENTO | E20: 0.2 | H20: =$B21 -> Agressivo-HORTELARIAS | I20: =VLOOKUP(H20,$B:$E,4,FALSE) -> 0.1
B21: =C21&"-"&D21 -> Agressivo-HORTELARIAS | C21: Agressivo | D21: HORTELARIAS | E21: 0.1
